data_portal_archiver/ckan_crawler.py
data_portal_archiver/ia_uploader.py
data_portal_archiver/main.py
data_portal_archiver/tests/__init__.py
data_portal_archiver/tests/test_ckan_crawler.py
data_portal_archiver/tests/test_ia_uploader.py
data_portal_archiver/utils.py
data_portal_archiver-0.1.14.dist-info/entry_points.txt
data_portal_archiver-0.1.14.dist-info/LICENSE
data_portal_archiver-0.1.14.dist-info/WHEEL
data_portal_archiver-0.1.14.dist-info/METADATA
data_portal_archiver-0.1.14.dist-info/RECORD
